dataloader/LIBSVM.py
dataloader/MULAN.py
dataloader/__init__.py
dataloader/config.py
dataloader/engine.py
dataloader/folds_generator.py
dataloader/synthetic/__init__.py
dataloader/synthetic/classification.py
dataloader/synthetic/engine.py
dataloader/synthetic/interval_regression.py
dataloader/synthetic/multilabels.py
dataloader/synthetic/ranking.py
problems/__init__.py
problems/generic.py
problems/classification/__init__.py
problems/classification/disambiguation.py
problems/classification/libsvm_experiments.py
problems/classification/semi_supervision_experiments.py
problems/classification/variational.py
problems/multilabel/__init__.py
problems/multilabel/disambiguation.py
problems/multilabel/mulan_experiments.py
problems/multilabel/synthetic_experiments.py
problems/multilabel/variational.py
problems/ranking/__init__.py
problems/ranking/disambiguation.py
problems/ranking/synthetic_experiments.py
problems/ranking/variational.py
problems/ranking/fassolver/__init__.py
problems/ranking/fassolver/basicsolver.py
problems/ranking/fassolver/embedding.py
problems/ranking/fassolver/engine.py
problems/ranking/fassolver/ilpsolver.py
problems/regression/__init__.py
problems/regression/disambiguation.py
problems/regression/synthetic_experiments.py
problems/regression/variational.py
weights/__init__.py
weights/graph_laplacian.py
weights/laplacian.py
weights/nearest_neighbors.py
weights/ridge_regression.py
plasp-1.0.0.dist-info/LICENSE.txt
plasp-1.0.0.dist-info/METADATA
plasp-1.0.0.dist-info/WHEEL
plasp-1.0.0.dist-info/top_level.txt
plasp-1.0.0.dist-info/RECORD
