Metadata-Version: 2.1
Name: plasp
Version: 1.0.0
Summary: Learning with Partial Supervision
Home-page: https://github.com/VivienCabannes/partial_labelling
Author: Vivien Cabannes
Author-email: vivien.cabannes@gmail.com
License: MIT
Download-URL: https://github.com/VivienCabannes/partial_labelling/archive/master.zip
Project-URL: Bug Tracker, https://github.com/pypa
Keywords: partial labeling weakly supervised learning plasp scalablemethod structured prediction
Platform: UNKNOWN
Classifier: Programming Language :: Python :: 3
Classifier: License :: OSI Approved :: MIT License
Classifier: Operating System :: OS Independent
Requires-Python: >=3.6
License-File: LICENSE.txt
